ipaddr.py
nsg.py
serialization.py
tag_selector.py
view.py
apps/__init__.py
apps/tags_app.py
apps/variables_app.py
apps/views_app.py
bin/__init__.py
bin/nsgsdk.py
net/__init__.py
net/happygears/__init__.py
net/happygears/nsgpython/__init__.py
net/happygears/nsgpython/apps/__init__.py
net/happygears/nsgpython/apps/impl/__init__.py
net/happygears/nsgpython/apps/impl/variable_app_response_converter.py
net/happygears/nsgpython/common/__init__.py
net/happygears/nsgpython/common/happy_gears_oids.py
net/happygears/nsgpython/common/pvar_reporter.py
net/happygears/nsgpython/common/tags_support.py
net/happygears/nw2/__init__.py
net/happygears/nw2/py/__init__.py
net/happygears/nw2/py/monitoring_data_type.py
net/happygears/nw2/py/sensor_data_type.py
net/happygears/nw2/py/py_wrappers/__init__.py
net/happygears/nw2/py/py_wrappers/hardware_component_class.py
net/happygears/nw2/py/py_wrappers/journaled_set.py
net/happygears/nw2/py/py_wrappers/py_aws_resource.py
net/happygears/nw2/py/py_wrappers/py_azure_resource.py
net/happygears/nw2/py/py_wrappers/py_chassis_alarm.py
net/happygears/nw2/py/py_wrappers/py_component.py
net/happygears/nw2/py/py_wrappers/py_device.py
net/happygears/nw2/py/py_wrappers/py_ipsec_tunnel.py
net/happygears/nw2/py/py_wrappers/py_mpls_tunnel.py
net/happygears/nw2/py/py_wrappers/py_network_interface.py
net/happygears/nw2/py/py_wrappers/py_protocol_descriptor.py
net/happygears/proto/NSGPythonSDK_pb2.py
net/happygears/proto/NSGPythonSDK_pb2_grpc.py
net/happygears/proto/NSG_pb2.py
net/happygears/proto/NSG_pb2_grpc.py
net/happygears/proto/__init__.py
variable_builders/__init__.py
variable_builders/aws_resource.py
variable_builders/azure_resource.py
variable_builders/base_variable_builder.py
variable_builders/chassis_alarms.py
variable_builders/device.py
variable_builders/fw_counters.py
variable_builders/hardware_component.py
variable_builders/interface.py
variable_builders/ipsec_tunnel.py
variable_builders/load_balancer.py
variable_builders/mpls_tunnel.py
nsg_python_sdk-0.0.4.dist-info/METADATA
nsg_python_sdk-0.0.4.dist-info/WHEEL
nsg_python_sdk-0.0.4.dist-info/entry_points.txt
nsg_python_sdk-0.0.4.dist-info/top_level.txt
nsg_python_sdk-0.0.4.dist-info/RECORD
