Metadata-Version: 2.1
Name: nsg-python-sdk
Version: 0.0.4
Summary: NetSpyGlass SDK
Home-page: https://github.com/happygears/nsg-python-sdk
Author: Happy Gears, Inc
License: Apache
Platform: UNKNOWN
Classifier: Programming Language :: Python :: 3.6
Classifier: Programming Language :: Python :: 3.7
Classifier: Programming Language :: Python :: 3.8
Classifier: Programming Language :: Python :: 3.9
Requires-Python: >=3.6
Requires-Dist: ipaddr
Requires-Dist: protobuf
Requires-Dist: click
Requires-Dist: sortedcontainers
